parman/__init__.py
parman/_version.py
parman/closure.py
parman/job.py
parman/metafunc.py
parman/scheduler.py
parman/treeleaf.py
parman/waitfuture.py
parman/wrapper.py
parman/clerks/__init__.py
parman/clerks/base.py
parman/clerks/local.py
parman/clerks/localtemp.py
parman/runners/__init__.py
parman/runners/base.py
parman/runners/concurrent.py
parman/runners/dry.py
parman/runners/future.py
parman/runners/parsl.py
parman/runners/serial.py
parman/scripts/__init__.py
parman/scripts/clean_results.py
parman/scripts/sbatch_wait.py
Parman-0.4.3.dist-info/LICENSE.txt
Parman-0.4.3.dist-info/METADATA
Parman-0.4.3.dist-info/WHEEL
Parman-0.4.3.dist-info/entry_points.txt
Parman-0.4.3.dist-info/top_level.txt
Parman-0.4.3.dist-info/RECORD
