Metadata-Version: 2.1
Name: Parman
Version: 0.4.3
Summary: Parman extends Python concurrent.futures to facilitate parallel workflows
Author-email: Toon Verstraelen <toon.verstraelen@ugent.be>
License: GNU LESSER GENERAL PUBLIC LICENSE
Project-URL: Issues, https://github.com/reproducible-reporting/parman/issues
Project-URL: Source, https://github.com/reproducible-reporting/parman/
Project-URL: Changelog, https://github.com/reproducible-reporting/parman/blob/main/CHANGELOG.md
Classifier: Development Status :: 3 - Alpha
Classifier: Environment :: Console
Classifier: Intended Audience :: Science/Research
Classifier: Intended Audience :: Education
Classifier: License :: OSI Approved :: GNU Lesser General Public License v3 or later (LGPLv3+)
Classifier: Natural Language :: English
Classifier: Operating System :: POSIX :: Linux
Classifier: Programming Language :: Python :: 3
Classifier: Programming Language :: Python :: 3 :: Only
Classifier: Programming Language :: Python :: 3.10
Classifier: Programming Language :: Python :: 3.11
Classifier: Programming Language :: Python :: 3.12
Classifier: Topic :: Scientific/Engineering
Classifier: Topic :: System :: Distributed Computing
Requires-Python: >=3.10
License-File: LICENSE.txt
Requires-Dist: attrs >=23.1.0
Requires-Dist: cattrs >=23.1.2
Provides-Extra: dev
Requires-Dist: pytest ; extra == 'dev'
Requires-Dist: pytest-xdist ; extra == 'dev'
Requires-Dist: ase ; extra == 'dev'
Requires-Dist: parsl ; extra == 'dev'
Requires-Dist: numpy ; extra == 'dev'
Requires-Dist: matplotlib ; extra == 'dev'
